automock25/__init__.py
automock25/config.ini
automock25/controller.py
automock25/dpPath.py
automock25/excuteOrder.py
automock25/excuteOrder222.py
automock25/logging.conf
automock25/logset.py
automock25/main.py
automock25/order.csv
automock25/record.py
automock25/recordData.py
automock25/recordJob.py
automock25/status.py
automock25/testsession.py
automock25/testwebpage.py
automock25/ttt.py
automock25-0.3.3.dist-info/METADATA
automock25-0.3.3.dist-info/WHEEL
automock25-0.3.3.dist-info/top_level.txt
automock25-0.3.3.dist-info/RECORD
