Metadata-Version: 2.2
Name: automock25
Version: 0.3.3
Summary: 自动模拟充值
Author: peak
Author-email: your.email@example.com
Classifier: Development Status :: 3 - Alpha
Classifier: Intended Audience :: Developers
Classifier: License :: OSI Approved :: MIT License
Requires-Python: >=3.6
Requires-Dist: requests>=2.24.0
Requires-Dist: flask>=3.0.0
Requires-Dist: DataRecorder>=3.6.2
Requires-Dist: DrissionPage>=4.1.0.17
Dynamic: author
Dynamic: author-email
Dynamic: classifier
Dynamic: description-content-type
Dynamic: requires-dist
Dynamic: requires-python
Dynamic: summary
